odoo8_addon_partner_contact_lang-8.0.1.0.0-py2.7-nspkg.pth
odoo8_addon_partner_contact_lang-8.0.1.0.0.dist-info/top_level.txt
odoo8_addon_partner_contact_lang-8.0.1.0.0.dist-info/WHEEL
odoo8_addon_partner_contact_lang-8.0.1.0.0.dist-info/RECORD
odoo8_addon_partner_contact_lang-8.0.1.0.0.dist-info/metadata.json
odoo8_addon_partner_contact_lang-8.0.1.0.0.dist-info/DESCRIPTION.rst
odoo8_addon_partner_contact_lang-8.0.1.0.0.dist-info/METADATA
odoo8_addon_partner_contact_lang-8.0.1.0.0.dist-info/namespace_packages.txt
odoo_addons/partner_contact_lang/__openerp__.py
odoo_addons/partner_contact_lang/__init__.py
odoo_addons/partner_contact_lang/README.rst
odoo_addons/partner_contact_lang/models/res_partner.py
odoo_addons/partner_contact_lang/models/__init__.py
odoo_addons/partner_contact_lang/views/res_partner_view.xml
odoo_addons/partner_contact_lang/tests/__init__.py
odoo_addons/partner_contact_lang/tests/test_partner_contact_lang.py
odoo_addons/partner_contact_lang/static/description/icon.svg
odoo_addons/partner_contact_lang/static/description/icon.png
